mplib/pymp.cpython-311-x86_64-linux-gnu.so
mplib/py.typed
mplib/planner.py
mplib/__init__.py
mplib/urdf_utils.py
mplib/pymp/__init__.pyi
mplib/pymp/kinematics/__init__.pyi
mplib/pymp/kinematics/pinocchio.pyi
mplib/pymp/kinematics/kdl.pyi
mplib/pymp/collision_detection/__init__.pyi
mplib/pymp/collision_detection/fcl.pyi
mplib/pymp/planning/__init__.pyi
mplib/pymp/planning/ompl.pyi
mplib/kinematics/pinocchio.py
mplib/kinematics/__init__.py
mplib/kinematics/kdl.py
mplib/collision_detection/__init__.py
mplib/collision_detection/fcl.py
mplib/sapien_utils/urdf_exporter.py
mplib/sapien_utils/srdf_exporter.py
mplib/sapien_utils/conversion.py
mplib/sapien_utils/__init__.py
mplib/examples/constrained_planning.py
mplib/examples/moving_robot.py
mplib/examples/demo_setup.py
mplib/examples/detect_collision.py
mplib/examples/__init__.py
mplib/examples/demo.py
mplib/examples/two_stage_motion.py
mplib/examples/collision_avoidance.py
mplib/planning/ompl.py
mplib/planning/__init__.py
mplib.libs/liborocos-kdl-7cd27755.so.1.5.1
mplib.libs/libassimp-5cf00ea2.so.5.3.0
mplib.libs/libboost_atomic-25f80f16.so.1.84.0
mplib.libs/liburdfdom_world-9e7dd961.so.4.0
mplib.libs/liboctomap-8ab68fde.so.1.9.8
mplib.libs/libboost_filesystem-0ad33d61.so.1.84.0
mplib.libs/libboost_system-19984e4f.so.1.84.0
mplib.libs/libccd-9b5c265e.so.2.0
mplib.libs/libconsole_bridge-af0b97d0.so.1.0
mplib.libs/liburdfdom_model-77607f1e.so.4.0
mplib.libs/libboost_serialization-6847464d.so.1.84.0
mplib.libs/libfcl-45f3e159.so.0.7.0
mplib.libs/libompl-e2fa74e1.so.1.6.0
mplib.libs/liboctomath-8d1bf25c.so.1.9.8
mplib-0.2.1.dist-info/RECORD
mplib-0.2.1.dist-info/WHEEL
mplib-0.2.1.dist-info/LICENSE
mplib-0.2.1.dist-info/top_level.txt
mplib-0.2.1.dist-info/METADATA
