Metadata-Version: 2.1
Name: mplib
Version: 0.2.1
Summary: A lightweight motion planning library
Author-email: Minghua Liu <minghua@ucsd.edu>, Jiayuan Gu <jigu@ucsd.edu>, Kolin Guo <ruguo@ucsd.edu>, Xinsong Lin <x8lin@ucsd.edu>
Maintainer-email: Kolin Guo <ruguo@ucsd.edu>, Xinsong Lin <x8lin@ucsd.edu>
License: MIT License
Keywords: robotics,motion planning
Classifier: Operating System :: POSIX :: Linux
Classifier: Intended Audience :: Developers
Classifier: Intended Audience :: Education
Classifier: Intended Audience :: Other Audience
Classifier: Intended Audience :: Science/Research
Classifier: License :: OSI Approved :: MIT License
Classifier: Natural Language :: English
Classifier: Framework :: Robot Framework :: Tool
Classifier: Programming Language :: C++
Classifier: Programming Language :: Python :: 3.8
Classifier: Programming Language :: Python :: 3.9
Classifier: Programming Language :: Python :: 3.10
Classifier: Programming Language :: Python :: 3.11
Classifier: Programming Language :: Python :: 3.12
Classifier: Topic :: Education
Classifier: Topic :: Software Development :: Libraries :: Python Modules
Classifier: Topic :: Utilities
Requires-Python: >=3.8
License-File: LICENSE
Requires-Dist: numpy<2.0
Requires-Dist: toppra>=0.4.0
Requires-Dist: transforms3d>=0.3.1
